[
  {
    "type": "single",
    "page": "Landing",
    "block": "",
    "comment": "Сделана ли страница Landing?",
    "options": [
      {
        "skip": "52",
        "label": "Сделана полностью, дополнительной проверки не требуется.",
        "points": "15"
      },
      {
        "skip": "0",
        "label": "Сделана, но есть конкретные замечания к адаптивности.",
        "points": "15"
      },
      {
        "skip": "51",
        "label": "Сделана, но есть только общие замечания к отзывчивости.",
        "points": "15"
      },
      {
        "skip": "52",
        "label": "Не cделана.",
        "points": "0"
      }
    ]
  },
  {
    "type": "single",
    "page": "Landing",
    "block": "1000px",
    "comment": "Соответствует ли страница требованиям cross-check на ширине экрана 1000px?",
    "options": [
      {
        "skip": "14",
        "label": "Да, соответствует полностью, дополнительной проверки не требуется. Или не соответствует заявленным требованиям, но все замечания уже были указаны ранее.",
        "points": "0"
      },
      {
        "skip": "0",
        "label": "Есть новые замечания.",
        "points": "0"
      }
    ]
  },
  {
    "type": "single",
    "page": "Landing",
    "block": "1000px",
    "comment": "Отступы между элементами меню в хедере",
    "options": [
      {
        "skip": "0",
        "label": "в порядке",
        "points": "0"
      },
      {
        "skip": "0",
        "label": "нарушены",
        "points": "-1"
      }
    ]
  },
  {
    "type": "single",
    "page": "Landing",
    "block": "1000px",
    "comment": "Расположение элементов в блоке Watch your favorite animal online",
    "options": [
      {
        "skip": "0",
        "label": "в порядке",
        "points": "0"
      },
      {
        "skip": "0",
        "label": "нарушено",
        "points": "-1"
      }
    ]
  },
  {
    "type": "single",
    "page": "Landing",
    "block": "1000px",
    "comment": "Расположение элементов в блоке The Backstage",
    "options": [
      {
        "skip": "0",
        "label": "в порядке",
        "points": "0"
      },
      {
        "skip": "0",
        "label": "нарушено",
        "points": "-1"
      }
    ]
  },
  {
    "type": "single",
    "page": "Landing",
    "block": "1000px",
    "comment": "Не пропало растение в блоке The Backstage (растение может исчезнуть резко, может плавно уходить за край экрана)",
    "options": [
      {
        "skip": "0",
        "label": "нет, растение пропало",
        "points": "0"
      },
      {
        "skip": "0",
        "label": "да",
        "points": "-1"
      }
    ]
  },
  {
    "type": "single",
    "page": "Landing",
    "block": "1000px",
    "comment": "Расположение или отступы между карточками животных в блоке Pets",
    "options": [
      {
        "skip": "0",
        "label": "в порядке",
        "points": "0"
      },
      {
        "skip": "0",
        "label": "нарушены",
        "points": "-1"
      }
    ]
  },
  {
    "type": "single",
    "page": "Landing",
    "block": "1000px",
    "comment": "Расположение или отступы между кнопками вправо/влево в блоке Pets",
    "options": [
      {
        "skip": "0",
        "label": "в порядке",
        "points": "0"
      },
      {
        "skip": "0",
        "label": "нарушены",
        "points": "-1"
      }
    ]
  },
  {
    "type": "single",
    "page": "Landing",
    "block": "1000px",
    "comment": "Вид растений справа или слева в блоке Pets",
    "options": [
      {
        "skip": "0",
        "label": "в порядке",
        "points": "0"
      },
      {
        "skip": "0",
        "label": "нарушен",
        "points": "-1"
      }
    ]
  },
  {
    "type": "single",
    "page": "Landing",
    "block": "1000px",
    "comment": "Количество, расположение или отступы между отзывами в блоке Testimonials",
    "options": [
      {
        "skip": "0",
        "label": "в порядке",
        "points": "0"
      },
      {
        "skip": "0",
        "label": "нарушены",
        "points": "-1"
      }
    ]
  },
  {
    "type": "single",
    "page": "Landing",
    "block": "1000px",
    "comment": "Расположение кнопки leave feedback в блоке Testimonials",
    "options": [
      {
        "skip": "0",
        "label": "в порядке",
        "points": "0"
      },
      {
        "skip": "0",
        "label": "нарушено",
        "points": "-1"
      }
    ]
  },
  {
    "type": "single",
    "page": "Landing",
    "block": "1000px",
    "comment": "Вид растения справа в блоке Testimonials",
    "options": [
      {
        "skip": "0",
        "label": "в порядке",
        "points": "0"
      },
      {
        "skip": "0",
        "label": "нарушен",
        "points": "-1"
      }
    ]
  },
  {
    "type": "single",
    "page": "Landing",
    "block": "1000px",
    "comment": "Расположение элементов внутри формы Subscribe to our news в футере",
    "options": [
      {
        "skip": "0",
        "label": "в порядке",
        "points": "0"
      },
      {
        "skip": "0",
        "label": "нарушено",
        "points": "-1"
      }
    ]
  },
  {
    "type": "single",
    "page": "Landing",
    "block": "1000px",
    "comment": "Расположение кнопки donate for volunteers в футере",
    "options": [
      {
        "skip": "0",
        "label": "в порядке",
        "points": "0"
      },
      {
        "skip": "0",
        "label": "нарушено",
        "points": "-1"
      }
    ]
  },
  {
    "type": "single",
    "page": "Landing",
    "block": "1000px",
    "comment": "Отступы между иконками и именами соцсетей в футере",
    "options": [
      {
        "skip": "0",
        "label": "в порядке",
        "points": "0"
      },
      {
        "skip": "0",
        "label": "нарушены",
        "points": "-1"
      }
    ]
  },
  {
    "type": "single",
    "page": "Landing",
    "block": "1000px",
    "comment": "Отступы между элементами меню в футере",
    "options": [
      {
        "skip": "0",
        "label": "в порядке",
        "points": "0"
      },
      {
        "skip": "0",
        "label": "нарушены",
        "points": "-1"
      }
    ]
  },
  {
    "type": "single",
    "page": "Landing",
    "block": "640px",
    "comment": "Соответствует ли страница требованиям cross-check на ширине экрана 640px?",
    "options": [
      {
        "skip": "17",
        "label": "Да, соответствует полностью, дополнительной проверки не требуется. Или не соответствует заявленным требованиям, но все замечания уже были указаны ранее.",
        "points": "0"
      },
      {
        "skip": "0",
        "label": "Есть новые замечания.",
        "points": "0"
      }
    ]
  },
  {
    "type": "single",
    "page": "Landing",
    "block": "640px",
    "comment": "Меню не преобразовано в бургер меню в хедере",
    "options": [
      {
        "skip": "0",
        "label": "нет, сделано правильно",
        "points": "0"
      },
      {
        "skip": "0",
        "label": "да",
        "points": "-1"
      }
    ]
  },
  {
    "type": "single",
    "page": "Landing",
    "block": "640px",
    "comment": "Хедер не стал фиксированным",
    "options": [
      {
        "skip": "0",
        "label": "нет, стал фиксированным",
        "points": "0"
      },
      {
        "skip": "0",
        "label": "да",
        "points": "-1"
      }
    ]
  },
  {
    "type": "single",
    "page": "Landing",
    "block": "640px",
    "comment": "Расположение элементов в блоке Watch your favorite animal online",
    "options": [
      {
        "skip": "0",
        "label": "в порядке",
        "points": "0"
      },
      {
        "skip": "0",
        "label": "нарушено",
        "points": "-1"
      }
    ]
  },
  {
    "type": "single",
    "page": "Landing",
    "block": "640px",
    "comment": "Расположение элементов в блоке The Backstage",
    "options": [
      {
        "skip": "0",
        "label": "в порядке",
        "points": "0"
      },
      {
        "skip": "0",
        "label": "нарушено",
        "points": "-1"
      }
    ]
  },
  {
    "type": "single",
    "page": "Landing",
    "block": "640px",
    "comment": "Не появилось растение в блоке The Backstage",
    "options": [
      {
        "skip": "0",
        "label": "нет, растение появилось",
        "points": "0"
      },
      {
        "skip": "0",
        "label": "да",
        "points": "-1"
      }
    ]
  },
  {
    "type": "single",
    "page": "Landing",
    "block": "640px",
    "comment": "Количество, расположение или отступы между карточками животных в блоке Pets",
    "options": [
      {
        "skip": "0",
        "label": "в порядке",
        "points": "0"
      },
      {
        "skip": "0",
        "label": "нарушены",
        "points": "-1"
      }
    ]
  },
  {
    "type": "single",
    "page": "Landing",
    "block": "640px",
    "comment": "Расположение или отступы между кнопками вправо/влево в блоке Pets",
    "options": [
      {
        "skip": "0",
        "label": "в порядке",
        "points": "0"
      },
      {
        "skip": "0",
        "label": "нарушены",
        "points": "-1"
      }
    ]
  },
  {
    "type": "single",
    "page": "Landing",
    "block": "640px",
    "comment": "Вид растений справа или слева в блоке Pets",
    "options": [
      {
        "skip": "0",
        "label": "в порядке",
        "points": "0"
      },
      {
        "skip": "0",
        "label": "нарушен",
        "points": "-1"
      }
    ]
  },
  {
    "type": "single",
    "page": "Landing",
    "block": "640px",
    "comment": "Расположение элементов в блоке Pick and feed a friend",
    "options": [
      {
        "skip": "0",
        "label": "в порядке",
        "points": "0"
      },
      {
        "skip": "0",
        "label": "нарушено",
        "points": "-1"
      }
    ]
  },
  {
    "type": "single",
    "page": "Landing",
    "block": "640px",
    "comment": "Вид стрелок в блоке Pick and feed a friend",
    "options": [
      {
        "skip": "0",
        "label": "в порядке",
        "points": "0"
      },
      {
        "skip": "0",
        "label": "нарушен",
        "points": "-1"
      }
    ]
  },
  {
    "type": "single",
    "page": "Landing",
    "block": "640px",
    "comment": "Вид, расположение или отступы между отзывами в блоке Testimonials",
    "options": [
      {
        "skip": "0",
        "label": "в порядке",
        "points": "0"
      },
      {
        "skip": "0",
        "label": "нарушены",
        "points": "-1"
      }
    ]
  },
  {
    "type": "single",
    "page": "Landing",
    "block": "640px",
    "comment": "Расположение кнопки leave feedback в блоке Testimonials",
    "options": [
      {
        "skip": "0",
        "label": "в порядке",
        "points": "0"
      },
      {
        "skip": "0",
        "label": "нарушено",
        "points": "-1"
      }
    ]
  },
  {
    "type": "single",
    "page": "Landing",
    "block": "640px",
    "comment": "Вид растения справа в блоке Testimonials",
    "options": [
      {
        "skip": "0",
        "label": "в порядке",
        "points": "0"
      },
      {
        "skip": "0",
        "label": "нарушен",
        "points": "-1"
      }
    ]
  },
  {
    "type": "single",
    "page": "Landing",
    "block": "640px",
    "comment": "Не пропала форма Subscribe to our news в футере (она должна скрыться)",
    "options": [
      {
        "skip": "0",
        "label": "нет, форма пропала",
        "points": "0"
      },
      {
        "skip": "0",
        "label": "да",
        "points": "-1"
      }
    ]
  },
  {
    "type": "single",
    "page": "Landing",
    "block": "640px",
    "comment": "Расположение кнопки donate for volunteers в футере",
    "options": [
      {
        "skip": "0",
        "label": "в порядке",
        "points": "0"
      },
      {
        "skip": "0",
        "label": "нарушено",
        "points": "-1"
      }
    ]
  },
  {
    "type": "single",
    "page": "Landing",
    "block": "640px",
    "comment": "Расположение или отступы между иконками соцсетей в футере",
    "options": [
      {
        "skip": "0",
        "label": "в порядке",
        "points": "0"
      },
      {
        "skip": "0",
        "label": "нарушено",
        "points": "-1"
      }
    ]
  },
  {
    "type": "single",
    "page": "Landing",
    "block": "640px",
    "comment": "Отступы между элементами меню в футере",
    "options": [
      {
        "skip": "0",
        "label": "в порядке",
        "points": "0"
      },
      {
        "skip": "0",
        "label": "нарушены",
        "points": "-1"
      }
    ]
  },
  {
    "type": "single",
    "page": "Landing",
    "block": "320px",
    "comment": "Соответствует ли страница требованиям cross-check на ширине экрана 320px?",
    "options": [
      {
        "skip": "17",
        "label": "Да, соответствует полностью, дополнительной проверки не требуется. Или не соответствует заявленным требованиям, но все замечания уже были указаны ранее.",
        "points": "0"
      },
      {
        "skip": "0",
        "label": "Есть новые замечания.",
        "points": "0"
      }
    ]
  },
  {
    "type": "single",
    "page": "Landing",
    "block": "320px",
    "comment": "Нет бургер меню в хедере",
    "options": [
      {
        "skip": "0",
        "label": "нет, бургер меню сделано",
        "points": "0"
      },
      {
        "skip": "0",
        "label": "да",
        "points": "-1"
      }
    ]
  },
  {
    "type": "single",
    "page": "Landing",
    "block": "320px",
    "comment": "Расположение элементов в блоке Watch your favorite animal online",
    "options": [
      {
        "skip": "0",
        "label": "в порядке",
        "points": "0"
      },
      {
        "skip": "0",
        "label": "нарушено",
        "points": "-1"
      }
    ]
  },
  {
    "type": "single",
    "page": "Landing",
    "block": "320px",
    "comment": "Расположение элементов в блоке The Backstage",
    "options": [
      {
        "skip": "0",
        "label": "в порядке",
        "points": "0"
      },
      {
        "skip": "0",
        "label": "нарушено",
        "points": "-1"
      }
    ]
  },
  {
    "type": "single",
    "page": "Landing",
    "block": "320px",
    "comment": "Растение в блоке The Backstage наезжает на текст (точность расположения растения в блоке The Backstage не оцениваем, и баллы за то, что его нет, не снимаем)",
    "options": [
      {
        "skip": "0",
        "label": "нет, растение не наезжает на текст, или изображения нету вообще",
        "points": "0"
      },
      {
        "skip": "0",
        "label": "да",
        "points": "-1"
      }
    ]
  },
  {
    "type": "single",
    "page": "Landing",
    "block": "320px",
    "comment": "Количество, расположение или отступы между карточками животных в блоке Pets",
    "options": [
      {
        "skip": "0",
        "label": "в порядке",
        "points": "0"
      },
      {
        "skip": "0",
        "label": "нарушены",
        "points": "-1"
      }
    ]
  },
  {
    "type": "single",
    "page": "Landing",
    "block": "320px",
    "comment": "Не пропали кнопки вправо/влево в блоке Pets",
    "options": [
      {
        "skip": "0",
        "label": "нет, кнопки пропали",
        "points": "0"
      },
      {
        "skip": "0",
        "label": "да",
        "points": "-1"
      }
    ]
  },
  {
    "type": "single",
    "page": "Landing",
    "block": "320px",
    "comment": "Вид растений справа или слева в блоке Pets",
    "options": [
      {
        "skip": "0",
        "label": "в порядке",
        "points": "0"
      },
      {
        "skip": "0",
        "label": "нарушен",
        "points": "-1"
      }
    ]
  },
  {
    "type": "single",
    "page": "Landing",
    "block": "320px",
    "comment": "Расположение элементов в блоке Pick and feed a friend",
    "options": [
      {
        "skip": "0",
        "label": "в порядке",
        "points": "0"
      },
      {
        "skip": "0",
        "label": "нарушено",
        "points": "-1"
      }
    ]
  },
  {
    "type": "single",
    "page": "Landing",
    "block": "320px",
    "comment": "Вид стрелок в блоке Pick and feed a friend",
    "options": [
      {
        "skip": "0",
        "label": "в порядке",
        "points": "0"
      },
      {
        "skip": "0",
        "label": "нарушен",
        "points": "-1"
      }
    ]
  },
  {
    "type": "single",
    "page": "Landing",
    "block": "320px",
    "comment": "Расположение или отступы между отзывами в блоке Testimonials",
    "options": [
      {
        "skip": "0",
        "label": "в порядке",
        "points": "0"
      },
      {
        "skip": "0",
        "label": "нарушены",
        "points": "-1"
      }
    ]
  },
  {
    "type": "single",
    "page": "Landing",
    "block": "320px",
    "comment": "Расположение кнопки leave feedback в блоке Testimonials",
    "options": [
      {
        "skip": "0",
        "label": "в порядке",
        "points": "0"
      },
      {
        "skip": "0",
        "label": "нарушено",
        "points": "-1"
      }
    ]
  },
  {
    "type": "single",
    "page": "Landing",
    "block": "320px",
    "comment": "Вид растения справа в блоке Testimonials",
    "options": [
      {
        "skip": "0",
        "label": "в порядке",
        "points": "0"
      },
      {
        "skip": "0",
        "label": "нарушен",
        "points": "-1"
      }
    ]
  },
  {
    "type": "single",
    "page": "Landing",
    "block": "320px",
    "comment": "Вид или расположение основного логотипа в футере",
    "options": [
      {
        "skip": "0",
        "label": "в порядке",
        "points": "0"
      },
      {
        "skip": "0",
        "label": "нарушены",
        "points": "-1"
      }
    ]
  },
  {
    "type": "single",
    "page": "Landing",
    "block": "320px",
    "comment": "Расположение или отступы между иконками соцсетей в футере",
    "options": [
      {
        "skip": "0",
        "label": "в порядке",
        "points": "0"
      },
      {
        "skip": "0",
        "label": "нарушены",
        "points": "-1"
      }
    ]
  },
  {
    "type": "single",
    "page": "Landing",
    "block": "320px",
    "comment": "Не появилась форма Subscribe to our news, или нарушено расположение элементов внутри этой формы, в футере",
    "options": [
      {
        "skip": "0",
        "label": "нет, форма появилась, и элементы внутри расположены правильно",
        "points": "0"
      },
      {
        "skip": "0",
        "label": "да",
        "points": "-1"
      }
    ]
  },
  {
    "type": "single",
    "page": "Landing",
    "block": "320px",
    "comment": "Расположение кнопки donate for volunteers в футере",
    "options": [
      {
        "skip": "0",
        "label": "в порядке",
        "points": "0"
      },
      {
        "skip": "0",
        "label": "нарушено",
        "points": "-1"
      }
    ]
  },
  {
    "type": "single",
    "page": "Landing",
    "block": "320px",
    "comment": "Отступы между элементами меню в футере",
    "options": [
      {
        "skip": "0",
        "label": "в порядке",
        "points": "0"
      },
      {
        "skip": "0",
        "label": "нарушены",
        "points": "-1"
      }
    ]
  },
  {
    "type": "multi",
    "page": "Landing",
    "block": "responsive",
    "comment": "Растягиваем страницу на ширину больше 1600px, и плавно сужаем до ширины 320px. При этом:",
    "options": [
      {
        "skip": "0",
        "label": "В ходе изменения размера появляется горизонтальная полоса прокрутки.",
        "points": "-4"
      },
      {
        "skip": "0",
        "label": "Отсуствует хотя бы один элемент (кроме указанных или фоновых элементов), или есть лишний.",
        "points": "-2"
      },
      {
        "skip": "0",
        "label": "Есть элементы (кроме указанных или фоновых элементов), которые обрезаются или выходят за край экрана, хотя в дизайне они вписаны в границы.",
        "points": "-2"
      },
      {
        "skip": "0",
        "label": "В какой-либо момент, элементы (кроме указанных или фоновых элементов) наезжают на другие элементы, хотя во всех дизайнах между ними есть отступ.",
        "points": "-2"
      }
    ]
  },
  {
    "type": "single",
    "page": "Map",
    "block": "",
    "comment": "Сделана ли страница Map?",
    "options": [
      {
        "skip": "36",
        "label": "Сделана полностью, дополнительной проверки не требуется.",
        "points": "10"
      },
      {
        "skip": "0",
        "label": "Сделана, но есть конкретные замечания к адаптивности.",
        "points": "10"
      },
      {
        "skip": "35",
        "label": "Сделана, но есть только общие замечания к отзывчивости.",
        "points": "10"
      },
      {
        "skip": "36",
        "label": "Не cделана.",
        "points": "0"
      }
    ]
  },
  {
    "type": "single",
    "page": "Map",
    "block": "1000px",
    "comment": "Соответствует ли страница требованиям cross-check на ширине экрана 1000px?",
    "options": [
      {
        "skip": "11",
        "label": "Да, соответствует полностью, дополнительной проверки не требуется. Или не соответствует заявленным требованиям, но все замечания уже были указаны ранее.",
        "points": "0"
      },
      {
        "skip": "0",
        "label": "Есть новые замечания.",
        "points": "0"
      }
    ]
  },
  {
    "type": "single",
    "page": "Map",
    "block": "1000px",
    "comment": "Отступы между элементами меню в хедере",
    "options": [
      {
        "skip": "0",
        "label": "в порядке",
        "points": "0"
      },
      {
        "skip": "0",
        "label": "нарушены",
        "points": "-1"
      }
    ]
  },
  {
    "type": "single",
    "page": "Map",
    "block": "1000px",
    "comment": "Хедер не тянется на всю ширину, или элементы хедера горизонтально не фиксированы, при наличии горизонтальной полосы прокрутки",
    "options": [
      {
        "skip": "0",
        "label": "нет, хедер сделан правильно",
        "points": "0"
      },
      {
        "skip": "0",
        "label": "да",
        "points": "-1"
      }
    ]
  },
  {
    "type": "single",
    "page": "Map",
    "block": "1000px",
    "comment": "Полностью отсутствует изображение карты",
    "options": [
      {
        "skip": "0",
        "label": "нет, карта есть на странице",
        "points": "0"
      },
      {
        "skip": "0",
        "label": "да",
        "points": "-1"
      }
    ]
  },
  {
    "type": "single",
    "page": "Map",
    "block": "1000px",
    "comment": "На карте исчезают иконки животных, или их позиция на карте сильно смещается, более чем на 30px",
    "options": [
      {
        "skip": "0",
        "label": "нет, иконки животных работают правильно",
        "points": "0"
      },
      {
        "skip": "0",
        "label": "да",
        "points": "-1"
      }
    ]
  },
  {
    "type": "single",
    "page": "Map",
    "block": "1000px",
    "comment": "Отступы между кнопками + и -",
    "options": [
      {
        "skip": "0",
        "label": "в порядке",
        "points": "0"
      },
      {
        "skip": "0",
        "label": "нарушены",
        "points": "-1"
      }
    ]
  },
  {
    "type": "single",
    "page": "Map",
    "block": "1000px",
    "comment": "При просмотре карты кнопки + и - должны находиться на своей позиции внизу окна, отступая от нижнего края на 20px, и двигаться вместе с вертикальным скроллом, пока до расстояние до футера не станет 20px. Такой функционал не реализован (если расстояние по умолчанию получается меньше 20px, то визуально, кнопки могут не двигаться)",
    "options": [
      {
        "skip": "0",
        "label": "нет, функционал реализован правильно",
        "points": "0"
      },
      {
        "skip": "0",
        "label": "да",
        "points": "-1"
      }
    ]
  },
  {
    "type": "single",
    "page": "Map",
    "block": "1000px",
    "comment": "Футер не тянется на всю ширину, или элементы футера горизонтально не фиксированы, при наличии горизонтальной полосы прокрутки",
    "options": [
      {
        "skip": "0",
        "label": "нет, футер сделан правильно",
        "points": "0"
      },
      {
        "skip": "0",
        "label": "да",
        "points": "-1"
      }
    ]
  },
  {
    "type": "single",
    "page": "Map",
    "block": "1000px",
    "comment": "Расположение элементов внутри формы Subscribe to our news в футере",
    "options": [
      {
        "skip": "0",
        "label": "в порядке",
        "points": "0"
      },
      {
        "skip": "0",
        "label": "нарушено",
        "points": "-1"
      }
    ]
  },
  {
    "type": "single",
    "page": "Map",
    "block": "1000px",
    "comment": "Расположение кнопки donate for volunteers в футере",
    "options": [
      {
        "skip": "0",
        "label": "в порядке",
        "points": "0"
      },
      {
        "skip": "0",
        "label": "нарушено",
        "points": "-1"
      }
    ]
  },
  {
    "type": "single",
    "page": "Map",
    "block": "1000px",
    "comment": "Отступы между иконками и именами соцсетей в футере",
    "options": [
      {
        "skip": "0",
        "label": "в порядке",
        "points": "0"
      },
      {
        "skip": "0",
        "label": "нарушены",
        "points": "-1"
      }
    ]
  },
  {
    "type": "single",
    "page": "Map",
    "block": "1000px",
    "comment": "Отступы между элементами меню в футере",
    "options": [
      {
        "skip": "0",
        "label": "в порядке",
        "points": "0"
      },
      {
        "skip": "0",
        "label": "нарушены",
        "points": "-1"
      }
    ]
  },
  {
    "type": "single",
    "page": "Map",
    "block": "640px",
    "comment": "Соответствует ли страница требованиям cross-check на ширине экрана 640px?",
    "options": [
      {
        "skip": "11",
        "label": "Да, соответствует полностью, дополнительной проверки не требуется. Или не соответствует заявленным требованиям, но все замечания уже были указаны ранее.",
        "points": "0"
      },
      {
        "skip": "0",
        "label": "Есть новые замечания.",
        "points": "0"
      }
    ]
  },
  {
    "type": "single",
    "page": "Map",
    "block": "640px",
    "comment": "Меню не преобразовано в бургер меню в хедере",
    "options": [
      {
        "skip": "0",
        "label": "нет, сделано правильно",
        "points": "0"
      },
      {
        "skip": "0",
        "label": "да",
        "points": "-1"
      }
    ]
  },
  {
    "type": "single",
    "page": "Map",
    "block": "640px",
    "comment": "Хедер не стал фиксированным",
    "options": [
      {
        "skip": "0",
        "label": "нет, стал фиксированным",
        "points": "0"
      },
      {
        "skip": "0",
        "label": "да",
        "points": "-1"
      }
    ]
  },
  {
    "type": "single",
    "page": "Map",
    "block": "640px",
    "comment": "Хедер не тянется на всю ширину, или элементы хедера горизонтально не фиксированы, при наличии горизонтальной полосы прокрутки",
    "options": [
      {
        "skip": "0",
        "label": "нет, хедер сделан правильно",
        "points": "0"
      },
      {
        "skip": "0",
        "label": "да",
        "points": "-1"
      }
    ]
  },
  {
    "type": "single",
    "page": "Map",
    "block": "640px",
    "comment": "Полностью отсутствует изображение карты",
    "options": [
      {
        "skip": "0",
        "label": "нет, карта есть на странице",
        "points": "0"
      },
      {
        "skip": "0",
        "label": "да",
        "points": "-1"
      }
    ]
  },
  {
    "type": "single",
    "page": "Map",
    "block": "640px",
    "comment": "На карте исчезают иконки животных, или их позиция на карте сильно смещается, более чем на 30px",
    "options": [
      {
        "skip": "0",
        "label": "нет, иконки животных работают правильно",
        "points": "0"
      },
      {
        "skip": "0",
        "label": "да",
        "points": "-1"
      }
    ]
  },
  {
    "type": "single",
    "page": "Map",
    "block": "640px",
    "comment": "Не пропали кнопки + и -",
    "options": [
      {
        "skip": "0",
        "label": "нет, кнопки пропали",
        "points": "0"
      },
      {
        "skip": "0",
        "label": "да",
        "points": "-1"
      }
    ]
  },
  {
    "type": "single",
    "page": "Map",
    "block": "640px",
    "comment": "Футер не тянется на всю ширину, или элементы футера горизонтально не фиксированы, при наличии горизонтальной полосы прокрутки",
    "options": [
      {
        "skip": "0",
        "label": "нет, футер сделан правильно",
        "points": "0"
      },
      {
        "skip": "0",
        "label": "да",
        "points": "-1"
      }
    ]
  },
  {
    "type": "single",
    "page": "Map",
    "block": "640px",
    "comment": "Не пропала форма Subscribe to our news в футере (она должна скрыться)",
    "options": [
      {
        "skip": "0",
        "label": "нет, форма пропала",
        "points": "0"
      },
      {
        "skip": "0",
        "label": "да",
        "points": "-1"
      }
    ]
  },
  {
    "type": "single",
    "page": "Map",
    "block": "640px",
    "comment": "Расположение кнопки donate for volunteers в футере",
    "options": [
      {
        "skip": "0",
        "label": "в порядке",
        "points": "0"
      },
      {
        "skip": "0",
        "label": "нарушено",
        "points": "-1"
      }
    ]
  },
  {
    "type": "single",
    "page": "Map",
    "block": "640px",
    "comment": "Расположение или отступы между иконками соцсетей в футере",
    "options": [
      {
        "skip": "0",
        "label": "в порядке",
        "points": "0"
      },
      {
        "skip": "0",
        "label": "нарушены",
        "points": "-1"
      }
    ]
  },
  {
    "type": "single",
    "page": "Map",
    "block": "640px",
    "comment": "Отступы между элементами меню в футере",
    "options": [
      {
        "skip": "0",
        "label": "в порядке",
        "points": "0"
      },
      {
        "skip": "0",
        "label": "нарушены",
        "points": "-1"
      }
    ]
  },
  {
    "type": "single",
    "page": "Map",
    "block": "320px",
    "comment": "Соответствует ли страница требованиям cross-check на ширине экрана 320px?",
    "options": [
      {
        "skip": "10",
        "label": "Да, соответствует полностью, дополнительной проверки не требуется. Или не соответствует заявленным требованиям, но все замечания уже были указаны ранее.",
        "points": "0"
      },
      {
        "skip": "0",
        "label": "Есть новые замечания.",
        "points": "0"
      }
    ]
  },
  {
    "type": "single",
    "page": "Map",
    "block": "320px",
    "comment": "Нет бургер меню в хедере",
    "options": [
      {
        "skip": "0",
        "label": "нет, бургер меню сделано",
        "points": "0"
      },
      {
        "skip": "0",
        "label": "да",
        "points": "-1"
      }
    ]
  },
  {
    "type": "single",
    "page": "Map",
    "block": "320px",
    "comment": "Хедер не тянется на всю ширину, или элементы хедера горизонтально не фиксированы, при наличии горизонтальной полосы прокрутки",
    "options": [
      {
        "skip": "0",
        "label": "нет, хедер сделан правильно",
        "points": "0"
      },
      {
        "skip": "0",
        "label": "да",
        "points": "-1"
      }
    ]
  },
  {
    "type": "single",
    "page": "Map",
    "block": "320px",
    "comment": "Полностью отсутствует изображение карты",
    "options": [
      {
        "skip": "0",
        "label": "нет, карта есть на странице",
        "points": "0"
      },
      {
        "skip": "0",
        "label": "да",
        "points": "-1"
      }
    ]
  },
  {
    "type": "single",
    "page": "Map",
    "block": "320px",
    "comment": "На карте исчезают иконки животных, или их позиция на карте сильно смещается, более чем на 30px",
    "options": [
      {
        "skip": "0",
        "label": "нет, иконки животных работают правильно",
        "points": "0"
      },
      {
        "skip": "0",
        "label": "да",
        "points": "-1"
      }
    ]
  },
  {
    "type": "single",
    "page": "Map",
    "block": "320px",
    "comment": "Футер не тянется на всю ширину, или элементы футера горизонтально не фиксированы, при наличии горизонтальной полосы прокрутки",
    "options": [
      {
        "skip": "0",
        "label": "нет, футер сделан правильно",
        "points": "0"
      },
      {
        "skip": "0",
        "label": "да",
        "points": "-1"
      }
    ]
  },
  {
    "type": "single",
    "page": "Map",
    "block": "320px",
    "comment": "Вид или расположение основного логотипа в футере",
    "options": [
      {
        "skip": "0",
        "label": "в порядке",
        "points": "0"
      },
      {
        "skip": "0",
        "label": "нарушены",
        "points": "-1"
      }
    ]
  },
  {
    "type": "single",
    "page": "Map",
    "block": "320px",
    "comment": "Расположение или отступы между иконками соцсетей в футере",
    "options": [
      {
        "skip": "0",
        "label": "в порядке",
        "points": "0"
      },
      {
        "skip": "0",
        "label": "нарушены",
        "points": "-1"
      }
    ]
  },
  {
    "type": "single",
    "page": "Map",
    "block": "320px",
    "comment": "Не появилась форма Subscribe to our news, или нарушено расположение элементов внутри этой формы, в футере",
    "options": [
      {
        "skip": "0",
        "label": "нет, форма появилась, и элементы внутри расположены правильно",
        "points": "0"
      },
      {
        "skip": "0",
        "label": "да",
        "points": "-1"
      }
    ]
  },
  {
    "type": "single",
    "page": "Map",
    "block": "320px",
    "comment": "Расположение кнопки donate for volunteers в футере",
    "options": [
      {
        "skip": "0",
        "label": "в порядке",
        "points": "0"
      },
      {
        "skip": "0",
        "label": "нарушено",
        "points": "-1"
      }
    ]
  },
  {
    "type": "single",
    "page": "Map",
    "block": "320px",
    "comment": "Отступы между элементами меню в футере",
    "options": [
      {
        "skip": "0",
        "label": "в порядке",
        "points": "0"
      },
      {
        "skip": "0",
        "label": "нарушены",
        "points": "-1"
      }
    ]
  },
  {
    "type": "multi",
    "page": "Map",
    "block": "responsive",
    "comment": "Растягиваем страницу на ширину больше 1600px, и плавно сужаем до ширины 320px. При этом:",
    "options": [
      {
        "skip": "0",
        "label": "В хедере или футере не хватает составных элементов (кроме указанных), или есть лишние.",
        "points": "-2"
      },
      {
        "skip": "0",
        "label": "Элементы хедера или футера (кроме указанных), обрезаются или выходят за край экрана, хотя в дизайне они вписаны в границы.",
        "points": "-2"
      },
      {
        "skip": "0",
        "label": "В какой-либо момент, элементы хедера или футера (кроме указанных) наезжают на другие элементы, хотя во всех дизайнах между ними есть отступ.",
        "points": "-2"
      }
    ]
  },
  {
    "type": "single",
    "page": "Zoos",
    "block": "",
    "comment": "Сделана ли хотя бы одна из страниц Zoos?",
    "options": [
      {
        "skip": "42",
        "label": "Сделана полностью, дополнительной проверки не требуется.",
        "points": "10"
      },
      {
        "skip": "0",
        "label": "Сделана, но есть конкретные замечания к адаптивности.",
        "points": "10"
      },
      {
        "skip": "41",
        "label": "Сделана, но есть только общие замечания к отзывчивости.",
        "points": "10"
      },
      {
        "skip": "42",
        "label": "Не cделана.",
        "points": "0"
      }
    ]
  },
  {
    "type": "single",
    "page": "Zoos",
    "block": "1000px",
    "comment": "Соответствует ли страница требованиям cross-check на ширине экрана 1000px?",
    "options": [
      {
        "skip": "12",
        "label": "Да, соответствует полностью, дополнительной проверки не требуется. Или не соответствует заявленным требованиям, но все замечания уже были указаны ранее.",
        "points": "0"
      },
      {
        "skip": "0",
        "label": "Есть новые замечания.",
        "points": "0"
      }
    ]
  },
  {
    "type": "single",
    "page": "Zoos",
    "block": "1000px",
    "comment": "Отступы между элементами меню в хедере",
    "options": [
      {
        "skip": "0",
        "label": "в порядке",
        "points": "0"
      },
      {
        "skip": "0",
        "label": "нарушены",
        "points": "-1"
      }
    ]
  },
  {
    "type": "single",
    "page": "Zoos",
    "block": "1000px",
    "comment": "Вид сайдбара или иконок внутри",
    "options": [
      {
        "skip": "0",
        "label": "в порядке",
        "points": "0"
      },
      {
        "skip": "0",
        "label": "нарушен",
        "points": "-1"
      }
    ]
  },
  {
    "type": "single",
    "page": "Zoos",
    "block": "1000px",
    "comment": "Сайдбар должен перейти из состояния fixed в состояние sticky, и терять фиксировнное состояние при достижении блока Information (Giant Panda). Сайдбар продолжает ездить на всю длину",
    "options": [
      {
        "skip": "0",
        "label": "нет, сайдбар переходит в состояние sticky и останавливается в указанном месте",
        "points": "0"
      },
      {
        "skip": "2",
        "label": "да",
        "points": "-1"
      }
    ]
  },
  {
    "type": "single",
    "page": "Zoos",
    "block": "1000px",
    "comment": "Количество или расположение элементов с видео превью в карусели в блоке Animal Camera",
    "options": [
      {
        "skip": "0",
        "label": "в порядке",
        "points": "0"
      },
      {
        "skip": "0",
        "label": "нарушены",
        "points": "-1"
      }
    ]
  },
  {
    "type": "single",
    "page": "Zoos",
    "block": "1000px",
    "comment": "Расположение или отступы между кнопками вправо/влево в блоке Animal Camera",
    "options": [
      {
        "skip": "0",
        "label": "в порядке",
        "points": "0"
      },
      {
        "skip": "0",
        "label": "нарушены",
        "points": "-1"
      }
    ]
  },
  {
    "type": "single",
    "page": "Zoos",
    "block": "1000px",
    "comment": "Расположение элементов в блоке Information",
    "options": [
      {
        "skip": "0",
        "label": "в порядке",
        "points": "0"
      },
      {
        "skip": "0",
        "label": "нарушено",
        "points": "-1"
      }
    ]
  },
  {
    "type": "single",
    "page": "Zoos",
    "block": "1000px",
    "comment": "Вид растений справа или слева в блоке Information",
    "options": [
      {
        "skip": "0",
        "label": "в порядке",
        "points": "0"
      },
      {
        "skip": "0",
        "label": "нарушен",
        "points": "-1"
      }
    ]
  },
  {
    "type": "single",
    "page": "Zoos",
    "block": "1000px",
    "comment": "Расположение кнопки Donate",
    "options": [
      {
        "skip": "0",
        "label": "в порядке",
        "points": "0"
      },
      {
        "skip": "0",
        "label": "нарушено",
        "points": "-1"
      }
    ]
  },
  {
    "type": "single",
    "page": "Zoos",
    "block": "1000px",
    "comment": "Расположение элементов внутри формы Subscribe to our news в футере",
    "options": [
      {
        "skip": "0",
        "label": "в порядке",
        "points": "0"
      },
      {
        "skip": "0",
        "label": "нарушено",
        "points": "-1"
      }
    ]
  },
  {
    "type": "single",
    "page": "Zoos",
    "block": "1000px",
    "comment": "Расположение кнопки donate for volunteers в футере",
    "options": [
      {
        "skip": "0",
        "label": "в порядке",
        "points": "0"
      },
      {
        "skip": "0",
        "label": "нарушено",
        "points": "-1"
      }
    ]
  },
  {
    "type": "single",
    "page": "Zoos",
    "block": "1000px",
    "comment": "Отступы между иконками и именами соцсетей в футере",
    "options": [
      {
        "skip": "0",
        "label": "в порядке",
        "points": "0"
      },
      {
        "skip": "0",
        "label": "нарушены",
        "points": "-1"
      }
    ]
  },
  {
    "type": "single",
    "page": "Zoos",
    "block": "1000px",
    "comment": "Отступы между элементами меню в футере",
    "options": [
      {
        "skip": "0",
        "label": "в порядке",
        "points": "0"
      },
      {
        "skip": "0",
        "label": "нарушены",
        "points": "-1"
      }
    ]
  },
  {
    "type": "single",
    "page": "Zoos",
    "block": "640px",
    "comment": "Соответствует ли страница требованиям cross-check на ширине экрана 640px?",
    "options": [
      {
        "skip": "13",
        "label": "Да, соответствует полностью, дополнительной проверки не требуется. Или не соответствует заявленным требованиям, но все замечания уже были указаны ранее.",
        "points": "0"
      },
      {
        "skip": "0",
        "label": "Есть новые замечания.",
        "points": "0"
      }
    ]
  },
  {
    "type": "single",
    "page": "Zoos",
    "block": "640px",
    "comment": "Меню не преобразовано в бургер меню в хедере",
    "options": [
      {
        "skip": "0",
        "label": "нет, сделано правильно",
        "points": "0"
      },
      {
        "skip": "0",
        "label": "да",
        "points": "-1"
      }
    ]
  },
  {
    "type": "single",
    "page": "Zoos",
    "block": "640px",
    "comment": "Хедер не стал фиксированным",
    "options": [
      {
        "skip": "0",
        "label": "нет, стал фиксированным",
        "points": "0"
      },
      {
        "skip": "0",
        "label": "да",
        "points": "-1"
      }
    ]
  },
  {
    "type": "single",
    "page": "Zoos",
    "block": "640px",
    "comment": "Вид сайдбара или иконок внутри",
    "options": [
      {
        "skip": "0",
        "label": "в порядке",
        "points": "0"
      },
      {
        "skip": "0",
        "label": "нарушен",
        "points": "-1"
      }
    ]
  },
  {
    "type": "single",
    "page": "Zoos",
    "block": "640px",
    "comment": "Сайдбар должен перейти из состояния sticky в состояние static, т.е. прекратить реагировать на скролл. Сайдбар продолжает ездить",
    "options": [
      {
        "skip": "0",
        "label": "нет, сайдбар прекратил реагировать на скролл",
        "points": "0"
      },
      {
        "skip": "2",
        "label": "да",
        "points": "-1"
      }
    ]
  },
  {
    "type": "single",
    "page": "Zoos",
    "block": "640px",
    "comment": "Расположение или отступы между элементами с видео превью в карусели в блоке Animal Camera",
    "options": [
      {
        "skip": "0",
        "label": "в порядке",
        "points": "0"
      },
      {
        "skip": "0",
        "label": "нарушены",
        "points": "-1"
      }
    ]
  },
  {
    "type": "single",
    "page": "Zoos",
    "block": "640px",
    "comment": "Расположение или отступы между кнопками вправо/влево в блоке Animal Camera",
    "options": [
      {
        "skip": "0",
        "label": "в порядке",
        "points": "0"
      },
      {
        "skip": "0",
        "label": "нарушены",
        "points": "-1"
      }
    ]
  },
  {
    "type": "single",
    "page": "Zoos",
    "block": "640px",
    "comment": "Расположение элементов в блоке Information",
    "options": [
      {
        "skip": "0",
        "label": "в порядке",
        "points": "0"
      },
      {
        "skip": "0",
        "label": "нарушено",
        "points": "-1"
      }
    ]
  },
  {
    "type": "single",
    "page": "Zoos",
    "block": "640px",
    "comment": "Вид растений справа или слева в блоке Information",
    "options": [
      {
        "skip": "0",
        "label": "в порядке",
        "points": "0"
      },
      {
        "skip": "0",
        "label": "нарушен",
        "points": "-1"
      }
    ]
  },
  {
    "type": "single",
    "page": "Zoos",
    "block": "640px",
    "comment": "Расположение кнопки Donate",
    "options": [
      {
        "skip": "0",
        "label": "в порядке",
        "points": "0"
      },
      {
        "skip": "0",
        "label": "нарушено",
        "points": "-1"
      }
    ]
  },
  {
    "type": "single",
    "page": "Zoos",
    "block": "640px",
    "comment": "Не пропала форма Subscribe to our news в футере (она должна скрыться)",
    "options": [
      {
        "skip": "0",
        "label": "нет, форма пропала",
        "points": "0"
      },
      {
        "skip": "0",
        "label": "да",
        "points": "-1"
      }
    ]
  },
  {
    "type": "single",
    "page": "Zoos",
    "block": "640px",
    "comment": "Расположение кнопки donate for volunteers в футере",
    "options": [
      {
        "skip": "0",
        "label": "в порядке",
        "points": "0"
      },
      {
        "skip": "0",
        "label": "нарушено",
        "points": "-1"
      }
    ]
  },
  {
    "type": "single",
    "page": "Zoos",
    "block": "640px",
    "comment": "Расположение или отступы между иконками соцсетей в футере",
    "options": [
      {
        "skip": "0",
        "label": "в порядке",
        "points": "0"
      },
      {
        "skip": "0",
        "label": "нарушено",
        "points": "-1"
      }
    ]
  },
  {
    "type": "single",
    "page": "Zoos",
    "block": "640px",
    "comment": "Отступы между элементами меню в футере",
    "options": [
      {
        "skip": "0",
        "label": "в порядке",
        "points": "0"
      },
      {
        "skip": "0",
        "label": "нарушены",
        "points": "-1"
      }
    ]
  },
  {
    "type": "single",
    "page": "Zoos",
    "block": "320px",
    "comment": "Соответствует ли страница требованиям cross-check на ширине экрана 320px?",
    "options": [
      {
        "skip": "13",
        "label": "Да, соответствует полностью, дополнительной проверки не требуется. Или не соответствует заявленным требованиям, но все замечания уже были указаны ранее.",
        "points": "0"
      },
      {
        "skip": "0",
        "label": "Есть новые замечания.",
        "points": "0"
      }
    ]
  },
  {
    "type": "single",
    "page": "Zoos",
    "block": "320px",
    "comment": "Нет бургер меню в хедере",
    "options": [
      {
        "skip": "0",
        "label": "нет, бургер меню сделано",
        "points": "0"
      },
      {
        "skip": "0",
        "label": "да",
        "points": "-1"
      }
    ]
  },
  {
    "type": "single",
    "page": "Zoos",
    "block": "320px",
    "comment": "Вид сайдбара",
    "options": [
      {
        "skip": "0",
        "label": "в порядке",
        "points": "0"
      },
      {
        "skip": "0",
        "label": "нарушен",
        "points": "-1"
      }
    ]
  },
  {
    "type": "single",
    "page": "Zoos",
    "block": "320px",
    "comment": "Количество или отступы между иконками животных в сайдбаре",
    "options": [
      {
        "skip": "0",
        "label": "в порядке",
        "points": "0"
      },
      {
        "skip": "0",
        "label": "нарушены",
        "points": "-1"
      }
    ]
  },
  {
    "type": "single",
    "page": "Zoos",
    "block": "320px",
    "comment": "Количесто, расположение или отступы между элементами с видео превью в карусели в блоке Animal Camera",
    "options": [
      {
        "skip": "0",
        "label": "в порядке",
        "points": "0"
      },
      {
        "skip": "0",
        "label": "нарушены",
        "points": "-1"
      }
    ]
  },
  {
    "type": "single",
    "page": "Zoos",
    "block": "320px",
    "comment": "Не пропали кнопки вправо/влево в блоке Animal Camera",
    "options": [
      {
        "skip": "0",
        "label": "нет, кнопки пропали",
        "points": "0"
      },
      {
        "skip": "0",
        "label": "да",
        "points": "-1"
      }
    ]
  },
  {
    "type": "single",
    "page": "Zoos",
    "block": "320px",
    "comment": "Расположение элементов в блоке Information",
    "options": [
      {
        "skip": "0",
        "label": "в порядке",
        "points": "0"
      },
      {
        "skip": "0",
        "label": "нарушено",
        "points": "-1"
      }
    ]
  },
  {
    "type": "single",
    "page": "Zoos",
    "block": "320px",
    "comment": "Вид растений справа или слева в блоке Information",
    "options": [
      {
        "skip": "0",
        "label": "в порядке",
        "points": "0"
      },
      {
        "skip": "0",
        "label": "нарушен",
        "points": "-1"
      }
    ]
  },
  {
    "type": "single",
    "page": "Zoos",
    "block": "320px",
    "comment": "Расположение кнопки Donate",
    "options": [
      {
        "skip": "0",
        "label": "в порядке",
        "points": "0"
      },
      {
        "skip": "0",
        "label": "нарушено",
        "points": "-1"
      }
    ]
  },
  {
    "type": "single",
    "page": "Zoos",
    "block": "320px",
    "comment": "Вид или расположение основного логотипа в футере",
    "options": [
      {
        "skip": "0",
        "label": "в порядке",
        "points": "0"
      },
      {
        "skip": "0",
        "label": "нарушены",
        "points": "-1"
      }
    ]
  },
  {
    "type": "single",
    "page": "Zoos",
    "block": "320px",
    "comment": "Расположение или отступы между иконками соцсетей в футере",
    "options": [
      {
        "skip": "0",
        "label": "в порядке",
        "points": "0"
      },
      {
        "skip": "0",
        "label": "нарушены",
        "points": "-1"
      }
    ]
  },
  {
    "type": "single",
    "page": "Zoos",
    "block": "320px",
    "comment": "Не появилась форма Subscribe to our news, или нарушено расположение элементов внутри этой формы, в футере",
    "options": [
      {
        "skip": "0",
        "label": "нет, форма появилась, и элементы внутри расположены правильно",
        "points": "0"
      },
      {
        "skip": "0",
        "label": "да",
        "points": "-1"
      }
    ]
  },
  {
    "type": "single",
    "page": "Zoos",
    "block": "320px",
    "comment": "Расположение кнопки donate for volunteers в футере",
    "options": [
      {
        "skip": "0",
        "label": "в порядке",
        "points": "0"
      },
      {
        "skip": "0",
        "label": "нарушено",
        "points": "-1"
      }
    ]
  },
  {
    "type": "single",
    "page": "Zoos",
    "block": "320px",
    "comment": "Отступы между элементами меню в футере",
    "options": [
      {
        "skip": "0",
        "label": "в порядке",
        "points": "0"
      },
      {
        "skip": "0",
        "label": "нарушены",
        "points": "-1"
      }
    ]
  },
  {
    "type": "multi",
    "page": "Zoos",
    "block": "responsive",
    "comment": "Растягиваем страницу на ширину больше 1600px, и плавно сужаем до ширины 320px. При этом:",
    "options": [
      {
        "skip": "0",
        "label": "В ходе изменения размера появляется горизонтальная полоса прокрутки.",
        "points": "-4"
      },
      {
        "skip": "0",
        "label": "Отсуствует хотя бы один элемент (кроме указанных или фоновых элементов), или есть лишний.",
        "points": "-2"
      },
      {
        "skip": "0",
        "label": "Есть элементы (кроме указанных или фоновых элементов), которые обрезаются или выходят за край экрана, хотя в дизайне они вписаны в границы.",
        "points": "-2"
      },
      {
        "skip": "0",
        "label": "В какой-либо момент, элементы хедера или футера (кроме указанных или фоновых элементов) наезжают на другие элементы, хотя во всех дизайнах между ними есть отступ.",
        "points": "-2"
      }
    ]
  },
  {
    "type": "single",
    "page": "Donate",
    "block": "",
    "comment": "Сделана ли страница Donate?",
    "options": [
      {
        "skip": "24",
        "label": "Сделана полностью, дополнительной проверки не требуется.",
        "points": "5"
      },
      {
        "skip": "0",
        "label": "Сделана, но есть конкретные замечания к адаптивности.",
        "points": "5"
      },
      {
        "skip": "23",
        "label": "Сделана, но есть только общие замечания к отзывчивости.",
        "points": "5"
      },
      {
        "skip": "24",
        "label": "Не cделана.",
        "points": "0"
      }
    ]
  },
  {
    "type": "single",
    "page": "Donate",
    "block": "1000px",
    "comment": "Соответствует ли страница требованиям cross-check на ширине экрана 1000px?",
    "options": [
      {
        "skip": "6",
        "label": "Да, соответствует полностью, дополнительной проверки не требуется. Или не соответствует заявленным требованиям, но все замечания уже были указаны ранее.",
        "points": "0"
      },
      {
        "skip": "0",
        "label": "Есть новые замечания.",
        "points": "0"
      }
    ]
  },
  {
    "type": "single",
    "page": "Donate",
    "block": "1000px",
    "comment": "Отступы между элементами меню в хедере",
    "options": [
      {
        "skip": "0",
        "label": "в порядке",
        "points": "0"
      },
      {
        "skip": "0",
        "label": "нарушены",
        "points": "-1"
      }
    ]
  },
  {
    "type": "single",
    "page": "Donate",
    "block": "1000px",
    "comment": "Расположение элементов в блоке Pick and feed a friend",
    "options": [
      {
        "skip": "0",
        "label": "в порядке",
        "points": "0"
      },
      {
        "skip": "0",
        "label": "нарушено",
        "points": "-1"
      }
    ]
  },
  {
    "type": "single",
    "page": "Donate",
    "block": "1000px",
    "comment": "Расположение элементов внутри формы Subscribe to our news в футере",
    "options": [
      {
        "skip": "0",
        "label": "в порядке",
        "points": "0"
      },
      {
        "skip": "0",
        "label": "нарушено",
        "points": "-1"
      }
    ]
  },
  {
    "type": "single",
    "page": "Donate",
    "block": "1000px",
    "comment": "Расположение кнопки donate for volunteers в футере",
    "options": [
      {
        "skip": "0",
        "label": "в порядке",
        "points": "0"
      },
      {
        "skip": "0",
        "label": "нарушено",
        "points": "-1"
      }
    ]
  },
  {
    "type": "single",
    "page": "Donate",
    "block": "1000px",
    "comment": "Отступы между иконками и именами соцсетей в футере",
    "options": [
      {
        "skip": "0",
        "label": "в порядке",
        "points": "0"
      },
      {
        "skip": "0",
        "label": "нарушены",
        "points": "-1"
      }
    ]
  },
  {
    "type": "single",
    "page": "Donate",
    "block": "1000px",
    "comment": "Отступы между элементами меню в футере",
    "options": [
      {
        "skip": "0",
        "label": "в порядке",
        "points": "0"
      },
      {
        "skip": "0",
        "label": "нарушены",
        "points": "-1"
      }
    ]
  },
  {
    "type": "single",
    "page": "Donate",
    "block": "640px",
    "comment": "Соответствует ли страница требованиям cross-check на ширине экрана 640px?",
    "options": [
      {
        "skip": "7",
        "label": "Да, соответствует полностью, дополнительной проверки не требуется. Или не соответствует заявленным требованиям, но все замечания уже были указаны ранее.",
        "points": "0"
      },
      {
        "skip": "0",
        "label": "Есть новые замечания.",
        "points": "0"
      }
    ]
  },
  {
    "type": "single",
    "page": "Donate",
    "block": "640px",
    "comment": "Меню не преобразовано в бургер меню в хедере",
    "options": [
      {
        "skip": "0",
        "label": "нет, сделано правильно",
        "points": "0"
      },
      {
        "skip": "0",
        "label": "да",
        "points": "-1"
      }
    ]
  },
  {
    "type": "single",
    "page": "Donate",
    "block": "640px",
    "comment": "Хедер не стал фиксированным",
    "options": [
      {
        "skip": "0",
        "label": "нет, стал фиксированным",
        "points": "0"
      },
      {
        "skip": "0",
        "label": "да",
        "points": "-1"
      }
    ]
  },
  {
    "type": "single",
    "page": "Donate",
    "block": "640px",
    "comment": "Расположение элементов в блоке Pick and feed a friend",
    "options": [
      {
        "skip": "0",
        "label": "в порядке",
        "points": "0"
      },
      {
        "skip": "0",
        "label": "нарушено",
        "points": "-1"
      }
    ]
  },
  {
    "type": "single",
    "page": "Donate",
    "block": "640px",
    "comment": "Не пропала форма Subscribe to our news в футере (она должна скрыться)",
    "options": [
      {
        "skip": "0",
        "label": "нет, форма пропала",
        "points": "0"
      },
      {
        "skip": "0",
        "label": "да",
        "points": "-1"
      }
    ]
  },
  {
    "type": "single",
    "page": "Donate",
    "block": "640px",
    "comment": "Расположение кнопки donate for volunteers в футере",
    "options": [
      {
        "skip": "0",
        "label": "в порядке",
        "points": "0"
      },
      {
        "skip": "0",
        "label": "нарушено",
        "points": "-1"
      }
    ]
  },
  {
    "type": "single",
    "page": "Donate",
    "block": "640px",
    "comment": "Расположение или отступы между иконками соцсетей в футере",
    "options": [
      {
        "skip": "0",
        "label": "в порядке",
        "points": "0"
      },
      {
        "skip": "0",
        "label": "нарушено",
        "points": "-1"
      }
    ]
  },
  {
    "type": "single",
    "page": "Donate",
    "block": "640px",
    "comment": "Отступы между элементами меню в футере",
    "options": [
      {
        "skip": "0",
        "label": "в порядке",
        "points": "0"
      },
      {
        "skip": "0",
        "label": "нарушены",
        "points": "-1"
      }
    ]
  },
  {
    "type": "single",
    "page": "Donate",
    "block": "320px",
    "comment": "Соответствует ли страница требованиям cross-check на ширине экрана 320px?",
    "options": [
      {
        "skip": "7",
        "label": "Да, соответствует полностью, дополнительной проверки не требуется. Или не соответствует заявленным требованиям, но все замечания уже были указаны ранее.",
        "points": "0"
      },
      {
        "skip": "0",
        "label": "Есть новые замечания.",
        "points": "0"
      }
    ]
  },
  {
    "type": "single",
    "page": "Donate",
    "block": "320px",
    "comment": "Нет бургер меню в хедере",
    "options": [
      {
        "skip": "0",
        "label": "нет, бургер меню сделано",
        "points": "0"
      },
      {
        "skip": "0",
        "label": "да",
        "points": "-1"
      }
    ]
  },
  {
    "type": "single",
    "page": "Donate",
    "block": "320px",
    "comment": "Расположение элементов в блоке Pick and feed a friend",
    "options": [
      {
        "skip": "0",
        "label": "в порядке",
        "points": "0"
      },
      {
        "skip": "0",
        "label": "нарушено",
        "points": "-1"
      }
    ]
  },
  {
    "type": "single",
    "page": "Donate",
    "block": "320px",
    "comment": "Вид или расположение основного логотипа в футере",
    "options": [
      {
        "skip": "0",
        "label": "в порядке",
        "points": "0"
      },
      {
        "skip": "0",
        "label": "нарушены",
        "points": "-1"
      }
    ]
  },
  {
    "type": "single",
    "page": "Donate",
    "block": "320px",
    "comment": "Расположение или отступы между иконками соцсетей в футере",
    "options": [
      {
        "skip": "0",
        "label": "в порядке",
        "points": "0"
      },
      {
        "skip": "0",
        "label": "нарушены",
        "points": "-1"
      }
    ]
  },
  {
    "type": "single",
    "page": "Donate",
    "block": "320px",
    "comment": "Не появилась форма Subscribe to our news, или нарушено расположение элементов внутри этой формы, в футере",
    "options": [
      {
        "skip": "0",
        "label": "нет, форма появилась, и элементы внутри расположены правильно",
        "points": "0"
      },
      {
        "skip": "0",
        "label": "да",
        "points": "-1"
      }
    ]
  },
  {
    "type": "single",
    "page": "Donate",
    "block": "320px",
    "comment": "Расположение кнопки donate for volunteers в футере",
    "options": [
      {
        "skip": "0",
        "label": "в порядке",
        "points": "0"
      },
      {
        "skip": "0",
        "label": "нарушено",
        "points": "-1"
      }
    ]
  },
  {
    "type": "single",
    "page": "Donate",
    "block": "320px",
    "comment": "Отступы между элементами меню в футере",
    "options": [
      {
        "skip": "0",
        "label": "в порядке",
        "points": "0"
      },
      {
        "skip": "0",
        "label": "нарушены",
        "points": "-1"
      }
    ]
  },
  {
    "type": "multi",
    "page": "Donate",
    "block": "responsive",
    "comment": "Растягиваем страницу на ширину больше 1600px, и плавно сужаем до ширины 320px. При этом:",
    "options": [
      {
        "skip": "0",
        "label": "В ходе изменения размера появляется горизонтальная полоса прокрутки.",
        "points": "-4"
      },
      {
        "skip": "0",
        "label": "Отсуствует хотя бы один элемент (кроме указанных или фоновых элементов), или есть лишний.",
        "points": "-2"
      },
      {
        "skip": "0",
        "label": "Есть элементы (кроме указанных или фоновых элементов), которые обрезаются или выходят за край экрана, хотя в дизайне они вписаны в границы.",
        "points": "-2"
      },
      {
        "skip": "0",
        "label": "В какой-либо момент, элементы хедера или футера (кроме указанных или фоновых элементов) наезжают на другие элементы, хотя во всех дизайнах между ними есть отступ.",
        "points": "-2"
      }
    ]
  },
  {
    "type": "single",
    "page": "",
    "block": "",
    "comment": "Если вы уверены в проверке, нажмите Завершить",
    "options": [
    ]
  }
]